{
  "name": "Renec Token List",
  "logoURI": "https://img-portal-prod.s3.amazonaws.com/uploads/image/attachment/33974/logo512.png",
  "keywords": [
    "renec",
    "spl"
  ],
  "tags": {
    "stablecoin": {
      "name": "stablecoin",
      "description": "Tokens that are fixed to an external asset, e.g. the US dollar"
    },
    "ethereum": {
      "name": "ethereum",
      "description": "Asset bridged from ethereum"
    },
    "lp-token": {
      "name": "lp-token",
      "description": "Asset representing liquidity provider token"
    },
    "wrapped": {
      "name": "wrapped",
      "description": "Asset wrapped using wormhole bridge"
    },
    "leveraged": {
      "name": "leveraged",
      "description": "Leveraged asset"
    },
    "bull": {
      "name": "bull",
      "description": "Leveraged Bull asset"
    },
    "bear": {
      "name": "bear",
      "description": "Leveraged Bear asset"
    },
    "nft": {
      "name": "nft",
      "description": "Non-fungible token"
    },
    "security-token": {
      "name": "security-token",
      "description": "Tokens that are used to gain access to an electronically restricted resource"
    },
    "utility-token": {
      "name": "utility-token",
      "description": "Tokens that are designed to be spent within a certain blockchain ecosystem e.g. most of the SPL-Tokens"
    },
    "tokenized-stock": {
      "name": "tokenized-stock",
      "description": "Tokenized stocks are tokenized derivatives that represent traditional securities, particularly shares in publicly firms traded on regulated exchanges"
    }
  },
  "timestamp": "2021-03-03T19:57:21+0000",
  "tokens": [
    {
      "chainId": 102,
      "address": "vaXGtV2RhVvvigLDd77cZa7NR3omLLe9wStYiogGPs8",
      "symbol": "PAN",
      "name": "Pancake Coin",
      "decimals": 9,
      "logoURI": "https://raw.githubusercontent.com/renec-chain/rpl-token-registry/master/assets/mainnet/vaXGtV2RhVvvigLDd77cZa7NR3omLLe9wStYiogGPs8/logo.png",
      "tags": [
        "currency"
      ],
      "extensions": {
      }
    },
    {
      "chainId": 102,
      "address": "jwXRUeahAbU2iaUSic3TdgbPEezcmejY7Fv5Savpg4w",
      "symbol": "rUSDT",
      "name": "Wrapped Tether USDT",
      "decimals": 9,
      "logoURI": "https://raw.githubusercontent.com/renec-chain/rpl-token-registry/master/assets/mainnet/jwXRUeahAbU2iaUSic3TdgbPEezcmejY7Fv5Savpg4w/logo.svg",
      "tags": [
        "stablecoin"
      ],
      "extensions": {
      }
    },
    {
      "chainId": 102,
      "address": "Fzyyy8SQ6K9NTJ7vCemZmxx4pexL8ePuuK7SkU8B7BhU",
      "symbol": "rUSDC",
      "name": "Wrapped USD Coin",
      "decimals": 9,
      "logoURI": "https://raw.githubusercontent.com/renec-chain/rpl-token-registry/master/assets/mainnet/Fzyyy8SQ6K9NTJ7vCemZmxx4pexL8ePuuK7SkU8B7BhU/logo.svg",
      "tags": [
        "stablecoin"
      ],
      "extensions": {
      }
    },
    {
      "chainId": 102,
      "address": "MsT76FqGo4JDxLkq73X872VWN6yEWsRBpKUAyY5LFTR",
      "symbol": "VNDR",
      "name": "Vietnam Dong",
      "decimals": 9,
      "logoURI": "https://raw.githubusercontent.com/renec-chain/rpl-token-registry/master/assets/mainnet/MsT76FqGo4JDxLkq73X872VWN6yEWsRBpKUAyY5LFTR/logo.svg",
      "tags": [
        "fiatcoin"
      ],
      "extensions": {
      }
    },
    {
      "chainId": 102,
      "address": "FhYxQy2GCsVK5rZgtvYDpKuytPXv2R34cPFQg3QDvjT7",
      "symbol": "NGNR",
      "name": "Nigeria Naira",
      "decimals": 9,
      "logoURI": "https://raw.githubusercontent.com/renec-chain/rpl-token-registry/master/assets/mainnet/FhYxQy2GCsVK5rZgtvYDpKuytPXv2R34cPFQg3QDvjT7/logo.svg",
      "tags": [
        "fiatcoin"
      ],
      "extensions": {
      }
    },
    {
      "chainId": 102,
      "address": "6HXkLhS4khE9RzGpNytzhuaon3egDK5mjBesUeKzNjEw",
      "symbol": "MYRR",
      "name": "Malaysia Ringgit",
      "decimals": 9,
      "logoURI": "https://raw.githubusercontent.com/renec-chain/rpl-token-registry/master/assets/mainnet/6HXkLhS4khE9RzGpNytzhuaon3egDK5mjBesUeKzNjEw/logo.svg",
      "tags": [
        "fiatcoin"
      ],
      "extensions": {
      }
    },
    {
      "chainId": 102,
      "address": "4Q89182juiadeFgGw3fupnrwnnDmBhf7e7fHWxnUP3S3",
      "symbol": "reUSD",
      "name": "reUSD",
      "decimals": 9,
      "logoURI": "https://raw.githubusercontent.com/renec-chain/rpl-token-registry/master/assets/mainnet/4Q89182juiadeFgGw3fupnrwnnDmBhf7e7fHWxnUP3S3/logo.png",
      "tags": [
        "stablecoin"
      ],
      "extensions": {
      }
    },
    {
      "chainId": 101,
      "address": "2Cx8kN9R1Anoh8HgoPaPPRE5FjQhgKNNem7Z6nKAc1p8",
      "symbol": "MemeFi",
      "name": "Meme Finance",
      "decimals": 9,
      "logoURI": "https://raw.githubusercontent.com/renec-chain/rpl-token-registry/master/assets/mainnet/2Cx8kN9R1Anoh8HgoPaPPRE5FjQhgKNNem7Z6nKAc1p8/logo.png.jpg",
      "tags": [
        "community-token"
      ],
      "extensions": {
        "discord": "https://discord.gg/gVCbUqNQrZ",
        "twitter": "https://twitter.com/MemeFi01"
      }
    },
    {
      "chainId": 101,
      "address": "DA22tiueni7Sm8eha7vkWPsEacpJWSPYr2HQfeh9upUp",
      "symbol": "VNLA",
      "name": "VanillaSwap Token",
      "decimals": 9,
      "logoURI": "https://raw.githubusercontent.com/renec-chain/rpl-token-registry/master/assets/mainnet/DA22tiueni7Sm8eha7vkWPsEacpJWSPYr2HQfeh9upUp/logo.png",
      "tags": [
        "utility-token"
      ],
      "extensions": {
      }
    },
    {
      "chainId": 101,
      "address": "4Q89182juiadeFgGw3fupnrwnnDmBhf7e7fHWxnUP3S3",
      "symbol": "reUSD",
      "name": "reUSD",
      "decimals": 9,
      "logoURI": "https://raw.githubusercontent.com/renec-chain/rpl-token-registry/master/assets/mainnet/4Q89182juiadeFgGw3fupnrwnnDmBhf7e7fHWxnUP3S3/logo.png",
      "tags": [
        "stablecoin"
      ],
      "extensions": {
      }
    },
    {
      "chainId": 101,
      "address": "GwPQTMg3eMVpDTEE3daZDtGsBtNHBK3X47dbBJvXUzF4",
      "symbol": "reBTC",
      "name": "reBTC",
      "decimals": 9,
      "logoURI": "https://raw.githubusercontent.com/renec-chain/rpl-token-registry/master/assets/mainnet/GwPQTMg3eMVpDTEE3daZDtGsBtNHBK3X47dbBJvXUzF4/logo.png",
      "tags": [
        "wrapped-coin"
      ],
      "extensions": {
      }
    },
    {
      "chainId": 101,
      "address": "GwGh3b7iNibT3gpGn6SwZA9xZme7Th4NZmuGVD75jpZL",
      "symbol": "reETH",
      "name": "reETH",
      "decimals": 9,
      "logoURI": "https://raw.githubusercontent.com/renec-chain/rpl-token-registry/master/assets/mainnet/GwGh3b7iNibT3gpGn6SwZA9xZme7Th4NZmuGVD75jpZL/logo.png",
      "tags": [
        "wrapped-coin"
      ],
      "extensions": {
      }
    },
    {
      "chainId": 101,
      "address": "23gvCwffARjM6qwygoWieYNWtwGjZD5Zatf95tWWQ8P5",
      "name": "NemoSwap",
      "symbol": "NEMO",
      "decimals": 9,
      "logoURI": "https://easytokenbucket.s3.amazonaws.com/tl53fhpapxb5g3nydp7l3dqwbrd3",
      "tags": [
        "utility-token"
      ],
      "extensions": {
      }
    },
    {
      "chainId": 101,
      "address": "Co4mpNrpMtZVmcPPVAZcVmeasuLW5XZSo3HxL6fEcv4E",
      "name": "Metachain",
      "symbol": "META",
      "decimals": 9,
      "logoURI": "https://easytokenbucket.s3.amazonaws.com/oml855vrh3qo0f8zehjw0cn3d19g",
      "tags": [
        "utility-token"
      ],
      "extensions": {
      }
    },
    {
      "chainId": 101,
      "address": "BDoXvPCEfipDmtbGo4Cvhi3HgrpvZMUq1ebymJ9WeYo",
      "name": "C3X Token",
      "symbol": "CEX",
      "decimals": 9,
      "logoURI": "https://easytokenbucket.s3.amazonaws.com/dv0oev5vu2o7ow60wwasht5vr7vu",
      "tags": [
        "utility-token"
      ],
      "extensions": {
      }
    },
    {
      "chainId": 101,
      "address": "FkQUqVZh7tbdetHSNZTyJjbNddGRccQJvqjfu3pxHMFj",
      "name": "JackSparrow",
      "symbol": "Arrow",
      "decimals": 9,
      "logoURI": "https://easytokenbucket.s3.amazonaws.com/e5wjybwgbjxm144vazgw26rrjvvi",
      "tags": [
        "utility-token"
      ],
      "extensions": {
      }
    },
    {
      "chainId": 101,
      "address": "HvLdkUWTNakJ5iey3RjAuFPQEtvsR1pE391vLtwcTjhN",
      "name": "Banh Mi",
      "symbol": "BaMi",
      "decimals": 9,
      "logoURI": "https://easytokenbucket.s3.amazonaws.com/45fwybqpvd8ob3cwgmazex9mykm2",
      "tags": [
        "utility-token"
      ],
      "extensions": {
      }
    },
    {
      "chainId": 101,
      "address": "3k4t8yC48T3hUmLeuGenEfcecBCfWwPj4wDhbuBBsnb1",
      "name": "Remitano",
      "symbol": "REM",
      "decimals": 9,
      "logoURI": "https://easytokenbucket.s3.amazonaws.com/60069crvhljctc3opewe4hymabte",
      "tags": [
        "utility-token"
      ],
      "extensions": {
      }
    },
    {
      "chainId": 101,
      "address": "Agrd4dUFLmMkXzZkT5V1HvQq7h4NntHUKKxneHRwqDC",
      "name": "PIZZA",
      "symbol": "PIZZA",
      "decimals": 9,
      "logoURI": "https://easytokenbucket.s3.amazonaws.com/0sz3smb4ipsjjud3z25khwcx84e5",
      "tags": [
        "utility-token"
      ],
      "extensions": {
      }
    },
    {
      "chainId": 101,
      "address": "EY7bx9NpoiUUxntsf4LQuNWMJ8x6zfYgd1N2DsG1EtxA",
      "name": "Turtle Ninja",
      "symbol": "NINJA",
      "decimals": 9,
      "logoURI": "https://easytokenbucket.s3.amazonaws.com/oezk0pn794ggg02gz1wyhe72k7rc",
      "tags": [
        "utility-token"
      ],
      "extensions": {
      }
    },
    {
      "chainId": 101,
      "address": "9tkDVwnMUH9qHFtz42FRosuZEmSQxtJBTYQHo38XqLvr",
      "name": " king of memes",
      "symbol": "MEME",
      "decimals": 9,
      "logoURI": "https://easytokenbucket.s3.amazonaws.com/lwcbohn2wjk3b9ps006qul0uizcr",
      "tags": [
        "utility-token"
      ],
      "extensions": {
      }
    },
    {
      "chainId": 101,
      "address": "91xiRwDnBrHxmXzoskWv6H7NXCnzRmm7sRmKvkLBii3d",
      "name": "dFantasy",
      "symbol": "DFAN",
      "decimals": 9,
      "logoURI": "https://easytokenbucket.s3.amazonaws.com/13pr1vulgv3eu16n0wngansdwckb",
      "tags": [
        "utility-token"
      ],
      "extensions": {
      }
    },
    {
      "chainId": 101,
      "address": "GoXBZFLe7UhJp3U9F2fuWeXrA4nVG3ZbHJa7AwT3sctj",
      "name": "PEPE ON MONEY ",
      "symbol": "MPEP",
      "decimals": 9,
      "logoURI": "https://easytokenbucket.s3.amazonaws.com/3j12pfymudwpq853nkflagbsqcba",
      "tags": [
        "utility-token"
      ],
      "extensions": {
      }
    },
    {
      "chainId": 101,
      "address": "8bpaNebxWEHnNmRq8QMXs7kAYkKUMA89MAHEhtkiwi7k",
      "name": "Jawa",
      "symbol": "JAWA",
      "decimals": 9,
      "logoURI": "https://easytokenbucket.s3.amazonaws.com/i01beu2z66xus7pwe9udqfe3j0kk",
      "tags": [
        "utility-token"
      ],
      "extensions": {
      }
    },
    {
      "chainId": 101,
      "address": "BKU82VVraxTmPeBE2FrJcFJBZT8J22yi6GgVho2GEv6S",
      "name": "vausa kingdom",
      "symbol": "VsK",
      "decimals": 9,
      "logoURI": "https://easytokenbucket.s3.amazonaws.com/71hkuyc6ru6gb3zmfw4rllfz906s",
      "tags": [
        "utility-token"
      ],
      "extensions": {
      }
    },
    {
      "chainId": 101,
      "address": "55xwFBuWupD3AoqckcBmic2B6frDJzYUhJ3iEwXwXgdy",
      "name": "GAREN",
      "symbol": "GAR",
      "decimals": 9,
      "logoURI": "https://easytokenbucket.s3.amazonaws.com/qei8y5t15b9cnzc5tycty3ww19wu",
      "tags": [
        "utility-token"
      ],
      "extensions": {
      }
    },
    {
      "chainId": 101,
      "address": "C3rdn387kAwYPD9fLsWFYr47KSdmJXmvqQy96ToMS3P7",
      "name": "Ghost Coin",
      "symbol": "GSTC",
      "decimals": 9,
      "logoURI": "https://easytokenbucket.s3.amazonaws.com/13ly5iw2gt3aus7km4g72001wyw4",
      "tags": [
        "utility-token"
      ],
      "extensions": {
      }
    },
    {
      "chainId": 101,
      "address": "FHhdCcQhZpP3gm17v7B6UP1hpD78uy5KFCkrH9yV4ezq",
      "name": "Dollar Coin",
      "symbol": "DLCO",
      "decimals": 9,
      "logoURI": "https://easytokenbucket.s3.amazonaws.com/ijqcrz5z7vsha6rx3tzp6ngkuw0d",
      "tags": [
        "utility-token"
      ],
      "extensions": {
      }
    },
    {
      "chainId": 101,
      "address": "CMy2tgd6Lrczb1XAxHVqSbTZ7HedoJRkS86a8UAroL5m",
      "name": "Panda Coin",
      "symbol": "PANDA",
      "decimals": 9,
      "logoURI": "https://easytokenbucket.s3.amazonaws.com/bz52zl1o7ngae8ygyypo5r8u9239",
      "tags": [
        "utility-token"
      ],
      "extensions": {
      }
    },
    {
      "chainId": 101,
      "address": "4imnhY566Ds1xWtsenUPs5V4Q6rgc2dNx7q8i1diW8v2",
      "name": "UPBO Forever",
      "symbol": "UPBO",
      "decimals": 9,
      "logoURI": "https://easytokenbucket.s3.amazonaws.com/gaxiw3gwf6kckipo04exen207x12",
      "tags": [
        "utility-token"
      ],
      "extensions": {
      }
    },
    {
      "chainId": 101,
      "address": "Bi7zp2gfb53vF5DsD7x43juznx6NA3H4kmTStA3E1MrW",
      "name": "Dizzy Token",
      "symbol": "DiZZY",
      "decimals": 9,
      "logoURI": "https://easytokenbucket.s3.amazonaws.com/gvjgqlmswm1yq3ycepwyj96h1shw",
      "tags": [
        "utility-token"
      ],
      "extensions": {
      }
    },
    {
      "chainId": 101,
      "address": "7upNdAfxcctzpkzvod36y2ExwXdPwXYWY72u5xh2Absg",
      "name": "Virtual Tech Systems coin",
      "symbol": "VTSC",
      "decimals": 9,
      "logoURI": "https://easytokenbucket.s3.amazonaws.com/73tnkmftqo6m8pnutu3cc6e0nd4p",
      "tags": [
        "utility-token"
      ],
      "extensions": {
      }
    },
    {
      "chainId": 101,
      "address": "FmHf1c3ns4WD7HyUpzDRzmNgAKQeHAEjxoAMiNBZv9H2",
      "name": "Crypto Investment Insurance",
      "symbol": "CII",
      "decimals": 1,
      "logoURI": "https://easytokenbucket.s3.amazonaws.com/bdaxqyrv57ma22u4b5wfr3hbai82",
      "tags": [
        "utility-token"
      ],
      "extensions": {
      }
    },
    {
      "chainId": 101,
      "address": "7tT4h6WDGzWqSqWNS9gHgpaLxyBANu1ydwDhdc2TqXB7",
      "name": "Babson DAO",
      "symbol": "BDAO",
      "decimals": 9,
      "logoURI": "https://easytokenbucket.s3.amazonaws.com/5r8f38dyp5u294nohqdg09kx76se",
      "tags": [
        "utility-token"
      ],
      "extensions": {
      }
    },
    {
      "chainId": 101,
      "address": "3jhnAy4xqPLRq63Wpdc74kp2BAx2HQBTA5akEvfbSEwp",
      "name": "Wolfverine",
      "symbol": "WOLF",
      "decimals": 9,
      "logoURI": "https://easytokenbucket.s3.amazonaws.com/c95exmzzk84oxrlgr83jnkimeym5",
      "tags": [
        "utility-token"
      ],
      "extensions": {
      }
    },
    {
      "chainId": 101,
      "address": "DGLK5cezycv1h9yvwwZxs7bhjfh497SumVqKhkQZR4ev",
      "name": "Coffee",
      "symbol": "CF",
      "decimals": 9,
      "logoURI": "https://easytokenbucket.s3.amazonaws.com/hdx1lzcomwcqzfrl8usx7izc6vfs",
      "tags": [
        "utility-token"
      ],
      "extensions": {
      }
    },
    {
      "chainId": 101,
      "address": "2j1tT3XV3DxEPgueZHKWUdya5DtZW1bfcKzxMrUYcyyx",
      "name": "Duck",
      "symbol": "DUCK",
      "decimals": 9,
      "logoURI": "https://easytokenbucket.s3.amazonaws.com/l5il9935j0mr8wi4ec21vxbx65ed",
      "tags": [
        "utility-token"
      ],
      "extensions": {
      }
    },
    {
      "chainId": 101,
      "address": "AoyGzve9cSs64HCUnvyZtUwcqY8hnHWCsQSAE7Rk1Dcx",
      "name": "Blog Nguyen Nam Thang",
      "symbol": "BNNT",
      "decimals": 9,
      "logoURI": "https://easytokenbucket.s3.amazonaws.com/qjohc4lxndjhsigal9pxs3ttpca9",
      "tags": [
        "utility-token"
      ],
      "extensions": {
      }
    },
    {
      "chainId": 101,
      "address": "2m93sKZpeMKwo8axqKRh67jTRWBSn7Vvx7nwRBY6t6SV",
      "name": "Love",
      "symbol": "LOVE",
      "decimals": 9,
      "logoURI": "https://easytokenbucket.s3.amazonaws.com/oe64i68lzounexg50xds4z41too5",
      "tags": [
        "utility-token"
      ],
      "extensions": {
      }
    },
    {
      "chainId": 101,
      "address": "84sjtkmcetbAxzMiKEaGnapzCfR956jJgMcgPXVVRw3m",
      "name": "Suon Bi Cha",
      "symbol": "SBC",
      "decimals": 9,
      "logoURI": "https://easytokenbucket.s3.amazonaws.com/2cjdmbbvgynb9ymvdnvik3anmdwl",
      "tags": [
        "utility-token"
      ],
      "extensions": {
      }
    },
    {
      "chainId": 101,
      "address": "4dzRUWQJhtcPJBkTqn6bV1tbk8zJKJbpBqYLmauCnYgK",
      "name": "Loofcoin",
      "symbol": "LFC",
      "decimals": 9,
      "logoURI": "https://easytokenbucket.s3.amazonaws.com/pqhofmqp6rvo085e6ho6gylyj08t",
      "tags": [
        "utility-token"
      ],
      "extensions": {
      }
    },
    {
      "chainId": 101,
      "address": "HscSdWFb6YgW8Y7s4Nf7myPnkTy3YPjARNEK7tWF58YQ",
      "name": "TRINITY",
      "symbol": "TRI",
      "decimals": 9,
      "logoURI": "https://easytokenbucket.s3.amazonaws.com/oesd79jt7gnro0yx2h14g36c2h21",
      "tags": [
        "utility-token"
      ],
      "extensions": {
      }
    },
    {
      "chainId": 101,
      "address": "FcahgbwLAs2wz5RApFXYMTxU7CBcLD9yWUASHrvxhw74",
      "name": "BAE",
      "symbol": "BABY",
      "decimals": 9,
      "logoURI": "https://easytokenbucket.s3.amazonaws.com/adxss429pw7zecxewfnajlkbm3eu",
      "tags": [
        "utility-token"
      ],
      "extensions": {
      }
    },
    {
      "chainId": 101,
      "address": "7z96S1iMAiXFMzfsZv6f5HTgZkfbM4G3aY1pLtmDijC7",
      "name": "Banker Club",
      "symbol": "BAC",
      "decimals": 9,
      "logoURI": "https://easytokenbucket.s3.amazonaws.com/6x1tt30tshoqa0ealnq7p2h3nlwk",
      "tags": [
        "utility-token"
      ],
      "extensions": {
      }
    },
    {
      "chainId": 101,
      "address": "6sRh7v1FbF8T55adsd25p7aXzKti625hawQ6JDPmNNzx",
      "name": "KENKOIN ",
      "symbol": "KENK",
      "decimals": 9,
      "logoURI": "https://easytokenbucket.s3.amazonaws.com/enky5qigqc0r8e3gycl20a8w1o01",
      "tags": [
        "utility-token"
      ],
      "extensions": {
      }
    },
    {
      "chainId": 101,
      "address": "BxGCAZLBGTLAjen51CFdf17vecFdwupGh4J6HSWTp9SH",
      "name": "Youplex",
      "symbol": "YPX",
      "decimals": 6,
      "logoURI": "https://easytokenbucket.s3.amazonaws.com/ao52dz81r7zi4j97gwkme806m767",
      "tags": [
        "utility-token"
      ],
      "extensions": {
      }
    },
    {
      "chainId": 101,
      "address": "6FomBrKS3w3n6EHSxUKiakRsfNmux29DiTwJT39ABf51",
      "name": "STROLLERS",
      "symbol": "STR",
      "decimals": 9,
      "logoURI": "https://easytokenbucket.s3.amazonaws.com/7czupozl5hnxjg9b3t1qizy2ufy9",
      "tags": [
        "utility-token"
      ],
      "extensions": {
      }
    },
    {
      "chainId": 101,
      "address": "4TdUWduRcBwPxkL4aR4AGfrd5e4hs4KaXa2FtvAKsTQ1",
      "name": "Bowlism Outlaw",
      "symbol": "BOWL",
      "decimals": 9,
      "logoURI": "https://easytokenbucket.s3.amazonaws.com/rlpr4ouat5y6mz4rgximi976iuu2",
      "tags": [
        "utility-token"
      ],
      "extensions": {
      }
    },
    {
      "chainId": 101,
      "address": "8A37pnjcbFhLZ9hctcwhB7Ggyraor3LJDtNLcxCjHW4N",
      "name": "MEOW MEOW COIN",
      "symbol": "MEO",
      "decimals": 9,
      "logoURI": "https://easytokenbucket.s3.amazonaws.com/3nk4rsadw02ez3wzxu5exu7ej3bg",
      "tags": [
        "utility-token"
      ],
      "extensions": {
      }
    },
    {
      "chainId": 101,
      "address": "AEvLwFHjfcKnxE4biCEVuRnXmhmgWkDXgAUeMatSDWiW",
      "name": "Debis",
      "symbol": "DBS",
      "decimals": 8,
      "logoURI": "https://easytokenbucket.s3.amazonaws.com/jqb3k3swzmxoitkzcwv8iyw03x6d",
      "tags": [
        "utility-token"
      ],
      "extensions": {
      }
    },
    {
      "chainId": 101,
      "address": "H5g5DL6YBbCeXKRZwdLnTuZAfKWyvyNFgZrQggqTHegq",
      "name": "TV Transport",
      "symbol": "TVT",
      "decimals": 9,
      "logoURI": "https://easytokenbucket.s3.amazonaws.com/pfx0tbb67eixzqlfwoe8j9nyvw7k",
      "tags": [
        "utility-token"
      ],
      "extensions": {
      }
    },
    {
      "chainId": 101,
      "address": "6KQXhCMx4ZF5HAaMt2x98p3uvPiDQxiGKwhZhNF6P8aL",
      "name": "VYVY",
      "symbol": "VEE",
      "decimals": 9,
      "logoURI": "https://easytokenbucket.s3.amazonaws.com/no4vhymxgga7sc0qdvqmnz8agyni",
      "tags": [
        "utility-token"
      ],
      "extensions": {
      }
    },
    {
      "chainId": 101,
      "address": "JE36sKeVSBY221TyPAtiq71uzGdWGtY64UBxUqj9ZgNW",
      "name": "NDCT Foundation Coin",
      "symbol": "NDCT",
      "decimals": 9,
      "logoURI": "https://easytokenbucket.s3.amazonaws.com/x8lyk7wq3w2el2ra9cmrqr6oq6mt",
      "tags": [
        "utility-token"
      ],
      "extensions": {
      }
    },
    {
      "chainId": 101,
      "address": "HQkuwTmSX1eJ572sWmQGuGx57i3vDHvVxwbBUpGBBDhF",
      "name": "HayRadeQua",
      "symbol": "rade",
      "decimals": 9,
      "logoURI": "https://easytokenbucket.s3.amazonaws.com/f0uq54fd9f5ecb0d3jdk5lk9snc1",
      "tags": [
        "utility-token"
      ],
      "extensions": {
      }
    },
    {
      "chainId": 101,
      "address": "2tckDnaR9qhE2i24pAu4kpNmw7mLQbJqVA7u42A7HEVN",
      "name": "MASTERLINKS IMPA",
      "symbol": "RIMPA",
      "decimals": 9,
      "logoURI": "https://easytokenbucket.s3.amazonaws.com/teibh2f8r5x82jeqil52qspxhr29",
      "tags": [
        "utility-token"
      ],
      "extensions": {
      }
    },
    {
      "chainId": 101,
      "address": "Dto37b9WTUU9iGekwjmvXPgJrFh3kzDosdgr2uYoNUZ2",
      "name": "Mely",
      "symbol": "mely",
      "decimals": 9,
      "logoURI": "https://easytokenbucket.s3.amazonaws.com/xszgfy23i9ooogniho8xz5f6bhx3",
      "tags": [
        "utility-token"
      ],
      "extensions": {
      }
    },
    {
      "chainId": 101,
      "address": "HkUYz5QQxmujKC1rjGNQTR7KQDNeDJFa9UDQkDRV2E9U",
      "name": "Ticket VIP",
      "symbol": "VIPP",
      "decimals": 9,
      "logoURI": "https://easytokenbucket.s3.amazonaws.com/h2fmz9srrzz41z3d8rb4dkyazozt",
      "tags": [
        "utility-token"
      ],
      "extensions": {
      }
    },
    {
      "chainId": 101,
      "address": "38h9f8gXFw1bXNa9LTcp9D9f51u5P53eTVetowxbLjQt",
      "name": "Ticket",
      "symbol": "CROWN",
      "decimals": 0,
      "logoURI": "https://easytokenbucket.s3.amazonaws.com/kp9tzl1900qy5hyaim45dwzzuj8z",
      "tags": [
        "utility-token"
      ],
      "extensions": {
      }
    },
    {
      "chainId": 101,
      "address": "Cvsfsi3vyT6ZzZpDTYtM8prLmB7J3d5xZzGufLqsbzVB",
      "name": "Tennis Coin",
      "symbol": "TNC",
      "decimals": 9,
      "logoURI": "https://easytokenbucket.s3.amazonaws.com/5zxmkev8p8udppi07ob5pccw0enm",
      "tags": [
        "utility-token"
      ],
      "extensions": {
      }
    },
    {
      "chainId": 101,
      "address": "FwBZc4Ymm5GJMJjpqqDao1sTYgCYP5ZoBTZq5qdy5kK7",
      "name": "Sports Network Cryptocurrency",
      "symbol": "SNC",
      "decimals": 9,
      "logoURI": "https://easytokenbucket.s3.amazonaws.com/mt0l35b2yx1go5398zgnva3r37uh",
      "tags": [
        "utility-token"
      ],
      "extensions": {
      }
    },
    {
      "chainId": 101,
      "address": "E4uRL9PA3aYZTfcodr265xv19C7eSc5Rctgh4xRFUa5Z",
      "name": "VICOIN",
      "symbol": "VIIN",
      "decimals": 9,
      "logoURI": "https://easytokenbucket.s3.amazonaws.com/ewdziumiyrzm0sfqw8nt0zd3mgll",
      "tags": [
        "utility-token"
      ],
      "extensions": {
      }
    },
    {
      "chainId": 101,
      "address": "Gs7jPkmjPKGhUfpYw9sAUKU6QuukfnCBb9JjzJikVAaF",
      "name": "rePEPE",
      "symbol": "rPepe",
      "decimals": 9,
      "logoURI": "https://easytokenbucket.s3.amazonaws.com/yid85c17cqf6i5a9b7tkewzwkv4s",
      "tags": [
        "utility-token"
      ],
      "extensions": {
      }
    },
    {
      "chainId": 101,
      "address": "4dD9gK8m335rBV58sx1bqDThkYURNjpniGrrhWmDEZyp",
      "name": "Lady",
      "symbol": "Lady",
      "decimals": 9,
      "logoURI": "https://easytokenbucket.s3.amazonaws.com/0gfo45dfayz8ch0he3w6n3zs1mee",
      "tags": [
        "utility-token"
      ],
      "extensions": {
      }
    },
    {
      "chainId": 101,
      "address": "2VdAN4qPmZyG2sD1oLs87JLGSwtWtKeco4wM7oCFVdRM",
      "name": "MASTERLINK COFFEE",
      "symbol": "MLCO",
      "decimals": 9,
      "logoURI": "https://easytokenbucket.s3.amazonaws.com/am4t0e4i7r4hp7p55acpchnnpnk2",
      "tags": [
        "utility-token"
      ],
      "extensions": {
      }
    },
    {
      "chainId": 101,
      "address": "4CjFtjGovCoeGUiLyrS3SR7YiNkL8VNU6uucnhozZD9Z",
      "name": "Cho Co Coin",
      "symbol": "ChoCo",
      "decimals": 9,
      "logoURI": "https://easytokenbucket.s3.amazonaws.com/f93phmm8ss2xvxm3cd93ksuy7k0z",
      "tags": [
        "utility-token"
      ],
      "extensions": {
      }
    },
    {
      "chainId": 101,
      "address": "5sk5BFJk6JcbmBBX1ZWLMz4EwXp9Rn3xkudhAK9Xmdjr",
      "name": "RENEC MONEY",
      "symbol": "RENM",
      "decimals": 9,
      "logoURI": "https://easytokenbucket.s3.amazonaws.com/u3kgrp3c1b3vu6hgp0uooaobn26d",
      "tags": [
        "utility-token"
      ],
      "extensions": {
      }
    },
    {
      "chainId": 101,
      "address": "5jvn2pBtYL1LuJh8SywX7NqT1dQfe9FsJ64zx9Q84R3x",
      "name": "CR7 Token",
      "symbol": "CRT",
      "decimals": 9,
      "logoURI": "https://easytokenbucket.s3.amazonaws.com/2m49je78wprdo4ciuf819mlf9og1",
      "tags": [
        "utility-token"
      ],
      "extensions": {
      }
    },
    {
      "chainId": 101,
      "address": "9ritC4taqC5RQxwNrZGT73nXfJr9xKfPDeyYNm1Pp3zK",
      "name": "PEDOGZ",
      "symbol": "PDZ",
      "decimals": 9,
      "logoURI": "https://easytokenbucket.s3.amazonaws.com/tbukkl9nj5pch6387ilb1y3k7sib",
      "tags": [
        "utility-token"
      ],
      "extensions": {
      }
    },
    {
      "chainId": 101,
      "address": "Emh29B2oKkfjjuniZ3yEDoYSqa72QBb49WMBQV6EzPN9",
      "name": "MAZI DOGE",
      "symbol": "MDG",
      "decimals": 9,
      "logoURI": "https://easytokenbucket.s3.amazonaws.com/45qq58wb4av435atf82x6133thlb",
      "tags": [
        "utility-token"
      ],
      "extensions": {
      }
    },
    {
      "chainId": 101,
      "address": "5ij77hmEoSvm8Yy8dkL5jLnTTTLwhiQjLgfeCtSiWTAF",
      "name": "TIREC",
      "symbol": "TRC",
      "decimals": 9,
      "logoURI": "https://easytokenbucket.s3.amazonaws.com/htj5pfv9xj9esjkww9u20s33jc1b",
      "tags": [
        "utility-token"
      ],
      "extensions": {
      }
    },
    {
      "chainId": 101,
      "address": "CTgp6ALtEUDG7S1PfRDT3xDcqzvd847ySESzzakYPCp5",
      "name": "Graphcai ",
      "symbol": "GPC",
      "decimals": 9,
      "logoURI": "https://easytokenbucket.s3.amazonaws.com/3h68nrtd5s14sdcfu20ho2xlsmji",
      "tags": [
        "utility-token"
      ],
      "extensions": {
      }
    },
    {
      "chainId": 101,
      "address": "2f1wDDxWx9dJF7C1ancokk6rju6LgmZFRh4Lb6MX4yRn",
      "name": "SUYA COIN",
      "symbol": "SUYA",
      "decimals": 9,
      "logoURI": "https://easytokenbucket.s3.amazonaws.com/mv53i8rq3vw7n9jn6y8tjlv19scg",
      "tags": [
        "utility-token"
      ],
      "extensions": {
      }
    },
    {
      "chainId": 101,
      "address": "Dtgtdpb49buvY5m1DYFFdB2EUDNtX1SrTBw6gkEQkXAV",
      "name": "BinhMyco",
      "symbol": "BMC",
      "decimals": 9,
      "logoURI": "https://easytokenbucket.s3.amazonaws.com/10zwuho3xfh9ie5zgc2q27c5gsu0",
      "tags": [
        "utility-token"
      ],
      "extensions": {
      }
    },
    {
      "chainId": 101,
      "address": "GGtSEJ2dxrnUwZTqKuWhHBYZieLG65KfDeWPKJmmAWv1",
      "name": "LemonadeLoot",
      "symbol": "LML",
      "decimals": 9,
      "logoURI": "https://easytokenbucket.s3.amazonaws.com/1gomp8bbupqt43z7ons67acy0fg0",
      "tags": [
        "utility-token"
      ],
      "extensions": {
      }
    },
    {
      "chainId": 101,
      "address": "Af6ajLhYwnP9x8pc8ESZoqsqAAQ3V9W3u6tTjjkwU1bg",
      "name": "MATERLINKS IMPA",
      "symbol": "IMPA",
      "decimals": 9,
      "logoURI": "https://easytokenbucket.s3.amazonaws.com/x2px5o0iy5y6n8pgclv5p77mi52w",
      "tags": [
        "utility-token"
      ],
      "extensions": {
      }
    },
    {
      "chainId": 101,
      "address": "DLocpjyRrc1V62jjKDQVdwT53nc7UQANm99MaWvGPhue",
      "name": "NGHE BANK",
      "symbol": "NBANK",
      "decimals": 9,
      "logoURI": "https://easytokenbucket.s3.amazonaws.com/qx7uzuzl13d3qsstylop57t9xq2x",
      "tags": [
        "utility-token"
      ],
      "extensions": {
      }
    },
    {
      "chainId": 101,
      "address": "21MfXx4gBzMXd1ZeVjoDCcPYiNC4uAafSE6CJVTdaQzR",
      "name": "Mcoin",
      "symbol": "MCN",
      "decimals": 9,
      "logoURI": "https://easytokenbucket.s3.amazonaws.com/3yozjd0lnck239e8ul8swopro9hk",
      "tags": [
        "utility-token"
      ],
      "extensions": {
      }
    },
    {
      "chainId": 101,
      "address": "9VdT8WhdDQjhg7FEz8guELuibTPd3jGq1A9hJuCvnxiR",
      "name": "Memeverse",
      "symbol": "MV",
      "decimals": 9,
      "logoURI": "https://easytokenbucket.s3.amazonaws.com/y5npu2v5e68gc19meiptoci8in0x",
      "tags": [
        "utility-token"
      ],
      "extensions": {
      }
    },
    {
      "chainId": 101,
      "address": "F9SMs8FC4NWKozeL7FoZvdKW8Zk3j8VTPT8M1osDAupE",
      "name": "MULTILEVEL CRYPTONETWORK",
      "symbol": "MCNET",
      "decimals": 9,
      "logoURI": "https://easytokenbucket.s3.amazonaws.com/djph8gddib32rs9tlng8ulik29rz",
      "tags": [
        "utility-token"
      ],
      "extensions": {
      }
    },
    {
      "chainId": 101,
      "address": "DsSfC7zi6wUcwbQRngLURSD8EyV4XrR3xcK4K4qmngmh",
      "name": "Tich",
      "symbol": "TIC",
      "decimals": 9,
      "logoURI": "https://easytokenbucket.s3.amazonaws.com/kezbut1dmrhtpl8z5y7wmpc41ova",
      "tags": [
        "utility-token"
      ],
      "extensions": {
      }
    },
    {
      "chainId": 101,
      "address": "2PQaNhNDCwKxgEzpzzP3UC9Xu5Zee6KDW9oGDDKRTLDU",
      "name": "DOCTOR",
      "symbol": "DOC",
      "decimals": 9,
      "logoURI": "https://easytokenbucket.s3.amazonaws.com/fr47dni3c1i4vxqhtnec2fj5gasa",
      "tags": [
        "utility-token"
      ],
      "extensions": {
      }
    },
    {
      "chainId": 101,
      "address": "E6wiRm7uw5EhtVxhpbMHKJ4Rvqi49hSsq3de5qUToaZB",
      "name": "DigitalPro CryptoNetwork",
      "symbol": "Dgpro",
      "decimals": 9,
      "logoURI": "https://easytokenbucket.s3.amazonaws.com/rzfxglpgu0fk6mr5ritpdhp116aa",
      "tags": [
        "utility-token"
      ],
      "extensions": {
      }
    },
    {
      "chainId": 101,
      "address": "7G3oDnJ9jnB4tw6StHu666UopzrxpbgeFpuSdywNWVBj",
      "name": "Grab Dieu Cay",
      "symbol": "AGRAB",
      "decimals": 9,
      "logoURI": "https://easytokenbucket.s3.amazonaws.com/467a5rdg3ne451icgml7vzhzna3a",
      "tags": [
        "utility-token"
      ],
      "extensions": {
      }
    },
    {
      "chainId": 101,
      "address": "31tbWtFTDDrRqNciYzSFSUuKbHn87RiPZhTJrEApq9A9",
      "name": "kind",
      "symbol": "KID",
      "decimals": 9,
      "logoURI": "https://easytokenbucket.s3.amazonaws.com/4ek9tlo66u7gwvt6ov64koqxjw7n",
      "tags": [
        "utility-token"
      ],
      "extensions": {
      }
    },
    {
      "chainId": 101,
      "address": "CUgCNnZEu474jyZrhXtyoM3mjAGcTYraGxCmhjbPoeNS",
      "name": "SolarBearRenec",
      "symbol": "SLR",
      "decimals": 9,
      "logoURI": "https://easytokenbucket.s3.amazonaws.com/ha6bwnhz71x4qtb259j5fufxa1z1",
      "tags": [
        "utility-token"
      ],
      "extensions": {
      }
    },
    {
      "chainId": 101,
      "address": "32G8dLyxtigyb7JXGdsScBQHPPNPucVziWafgaewcDj3",
      "name": "MEOMEO",
      "symbol": "MEOS",
      "decimals": 7,
      "logoURI": "https://easytokenbucket.s3.amazonaws.com/qtpjpg3vjv37lu9qak7ur0qjyena",
      "tags": [
        "utility-token"
      ],
      "extensions": {
      }
    },
    {
      "chainId": 101,
      "address": "AgSh2E2ZeUPxhKEZ9qiwowuotp1s6VVKSAXdCBZjJJGE",
      "name": "KaidenID",
      "symbol": "KAIID",
      "decimals": 7,
      "logoURI": "https://easytokenbucket.s3.amazonaws.com/vw19xagop03mg4cmrkrkts7m7wbw",
      "tags": [
        "utility-token"
      ],
      "extensions": {
      }
    },
    {
      "chainId": 101,
      "address": "EGvhvyKfUZycyed1kGgkRDzqUL9fd7yxXjF2HTQoDGEk",
      "name": "RENEC inu",
      "symbol": "RNCI",
      "decimals": 8,
      "logoURI": "https://easytokenbucket.s3.amazonaws.com/v017m60kc0mwexx4d23t1giuvyem",
      "tags": [
        "utility-token"
      ],
      "extensions": {
      }
    },
    {
      "chainId": 101,
      "address": "4eoZHd1KBEeKPRAoFE2KpKqPe1W6uC2hp6vjXKNztEjA",
      "name": "MoonCatCoin",
      "symbol": "MCC",
      "decimals": 9,
      "logoURI": "https://easytokenbucket.s3.amazonaws.com/zjftsqd0de4ei5tfbru5y4bn0lzf",
      "tags": [
        "utility-token"
      ],
      "extensions": {
      }
    },
    {
      "chainId": 101,
      "address": "4429h87CuYefsSByt6Ko9sUdGE93mrrZyq64ukHp6HpB",
      "name": "RocketDoggo",
      "symbol": "RDG",
      "decimals": 9,
      "logoURI": "https://easytokenbucket.s3.amazonaws.com/doo07umd83qgt88qln5lokyqkysn",
      "tags": [
        "utility-token"
      ],
      "extensions": {
      }
    },
    {
      "chainId": 101,
      "address": "2iwRnubAjXtAn7NschM9F6hVhLHSng3sfbrr6TqVFny1",
      "name": "PandaPump",
      "symbol": "PMP",
      "decimals": 9,
      "logoURI": "https://easytokenbucket.s3.amazonaws.com/5x1otvjtrhtdozogg4fq02cfqnh6",
      "tags": [
        "utility-token"
      ],
      "extensions": {
      }
    },
    {
      "chainId": 101,
      "address": "GcGcMU8TgbyuRJEGx2TewVsg4y9yyGtUtsLedeStqwHq",
      "name": "ShibaRenec",
      "symbol": "SBR",
      "decimals": 9,
      "logoURI": "https://easytokenbucket.s3.amazonaws.com/r83aez4llgbut73yem3tezw69gsw",
      "tags": [
        "utility-token"
      ],
      "extensions": {
      }
    },
    {
      "chainId": 101,
      "address": "BUW8MABJtCnCpVtC2kuWp9dMGvUrc3kJVRk6tqMYeKLW",
      "name": "FrogeCoin",
      "symbol": "FROGE",
      "decimals": 9,
      "logoURI": "https://easytokenbucket.s3.amazonaws.com/d68j6jyziz03zv5jg2ijromeql93",
      "tags": [
        "utility-token"
      ],
      "extensions": {
      }
    },
    {
      "chainId": 101,
      "address": "FWdsoLdjHkpLCRaXnr7YeVRbxCB99K42qMNtm4dGkuJf",
      "name": "esst ",
      "symbol": "SST",
      "decimals": 9,
      "logoURI": "https://easytokenbucket.s3.amazonaws.com/tn74uny1sur4tk54c7pfeyq53khh",
      "tags": [
        "utility-token"
      ],
      "extensions": {
      }
    },
    {
      "chainId": 101,
      "address": "CQQ8qeFrdEopb8xjDFXQ1pyKQhohsWHc9xubYZtPR4oK",
      "name": "INC",
      "symbol": "INC",
      "decimals": 9,
      "logoURI": "https://easytokenbucket.s3.amazonaws.com/y0mmhft5ys1pb4qmu8sawcrkmrix",
      "tags": [
        "utility-token"
      ],
      "extensions": {
      }
    },
    {
      "chainId": 101,
      "address": "2zHuvv2qyoPS2sEsY444nvUxQTYMPcsMsMNd4YkzKWNg",
      "name": "SASDOG",
      "symbol": "SDG",
      "decimals": 9,
      "logoURI": "https://easytokenbucket.s3.amazonaws.com/i5csfpgjuonjrnkyep11e06g7eyt",
      "tags": [
        "utility-token"
      ],
      "extensions": {
      }
    },
    {
      "chainId": 101,
      "address": "HnkGvpm5ntg4JEh3cUhBuWVMtmYNLkqx4iWX3uBFWee",
      "name": "TZ Renec minners",
      "symbol": "TZRM",
      "decimals": 9,
      "logoURI": "https://easytokenbucket.s3.amazonaws.com/6oltf2fg6k80e0pkk617yk0pwxgg",
      "tags": [
        "utility-token"
      ],
      "extensions": {
      }
    },
    {
      "chainId": 101,
      "address": "5nPogH3C1j1BGSopMuLfHcd2qndwV453cSPSBsLFpAQt",
      "name": "Strawberry",
      "symbol": "rSB",
      "decimals": 9,
      "logoURI": "https://easytokenbucket.s3.amazonaws.com/yv5ecif0dulne14tnxkmqkyd9b1x",
      "tags": [
        "utility-token"
      ],
      "extensions": {
      }
    },
    {
      "chainId": 101,
      "address": "CdivUSfH3PHj4X98j4xXEEVdt73DkUhfxRnLrtpP2siS",
      "name": "oracle",
      "symbol": "ORC",
      "decimals": 7,
      "logoURI": "https://easytokenbucket.s3.amazonaws.com/pd5lx8w8igdhwayhi4g4j1ny9kd3",
      "tags": [
        "utility-token"
      ],
      "extensions": {
      }
    },
    {
      "chainId": 101,
      "address": "BvD2FciHtkWeJdCzN3izStyqDwcv2rmsYbfWoYmjQtCg",
      "name": "SmaskMoney game",
      "symbol": "SMG",
      "decimals": 9,
      "logoURI": "https://easytokenbucket.s3.amazonaws.com/mn3o0v8sj70orizkd2sedzyqg63j",
      "tags": [
        "utility-token"
      ],
      "extensions": {
      }
    },
    {
      "chainId": 101,
      "address": "8p8gSJ64Sak82C5VRb967MUC4rx1ygjWsMFkEDpchTYt",
      "name": "DUC Foundation token",
      "symbol": "DUC",
      "decimals": 8,
      "logoURI": "https://easytokenbucket.s3.amazonaws.com/dlkdjwou4irglsdvi4feq34eaukp",
      "tags": [
        "utility-token"
      ],
      "extensions": {
      }
    },
    {
      "chainId": 101,
      "address": "2Ki8iV87EqduUAS5sRCdyox9s6YB9JteRYQSRb17nvw6",
      "name": "MOON",
      "symbol": "MOON",
      "decimals": 9,
      "logoURI": "https://easytokenbucket.s3.amazonaws.com/u1tqp0hvcx6jo09skzxhz0bh6jkx",
      "tags": [
        "utility-token"
      ],
      "extensions": {
      }
    },
    {
      "chainId": 101,
      "address": "9tqgjb3654VQ3KNne56ghh2S83x1gqzZfLXaZ7tQwKV",
      "name": "Wrapped DOGESHIBA",
      "symbol": "WDOSH",
      "decimals": 9,
      "logoURI": "https://easytokenbucket.s3.amazonaws.com/xg68uvilphxnjw7rxepc9vezjgxh",
      "tags": [
        "utility-token"
      ],
      "extensions": {
      }
    },
    {
      "chainId": 101,
      "address": "HPtwNYuzJZBXzqkGqmgags9oxWH88W5VNuW4grVSr7Uz",
      "name": "Tanpt",
      "symbol": "PTT",
      "decimals": 9,
      "logoURI": "https://easytokenbucket.s3.amazonaws.com/4gggii2naxg1hd30r0a5pj9c1kcc",
      "tags": [
        "utility-token"
      ],
      "extensions": {
      }
    },
    {
      "chainId": 101,
      "address": "GU4Cdg26PFU9EK2uDJ2vvSvTjQnNPDfuD56wkiR37H2o",
      "name": "Mooncoin",
      "symbol": "MOONC",
      "decimals": 9,
      "logoURI": "https://easytokenbucket.s3.amazonaws.com/gb61vzfcuvz1tupgxwnrgsg2voz4",
      "tags": [
        "utility-token"
      ],
      "extensions": {
      }
    },
    {
      "chainId": 101,
      "address": "JCVHzMtP6peQkTmoW46YNHyKQuoushF4WUhapphLdnSr",
      "name": "happy bird",
      "symbol": "BIRD",
      "decimals": 9,
      "logoURI": "https://easytokenbucket.s3.amazonaws.com/x1ygxwqnmil61xkyno0rkgef3dny",
      "tags": [
        "utility-token"
      ],
      "extensions": {
      }
    },
    {
      "chainId": 101,
      "address": "C8jRcLpa1kumEg9p49EVKkPWuYz8EgD5XWmCXG4r13Jv",
      "name": "CloudNec",
      "symbol": "CDC",
      "decimals": 9,
      "logoURI": "https://easytokenbucket.s3.amazonaws.com/q44ydu56f4tg38v8brzfymrwdtgt",
      "tags": [
        "utility-token"
      ],
      "extensions": {
      }
    },
    {
      "chainId": 101,
      "address": "2pfRAWrVVm9mLa8TbzbvgNPKwsPbcDHUyQJZmYfDLQnd",
      "name": "AEPay Coin",
      "symbol": "AE",
      "decimals": 9,
      "logoURI": "https://easytokenbucket.s3.amazonaws.com/9y26nagju6u8973wytev5gvsxbx9",
      "tags": [
        "utility-token"
      ],
      "extensions": {
      }
    },
    {
      "chainId": 101,
      "address": "H7y4ADadmfBLDDaJmDY4LF81yPaUp69oYTr9UEN1KywV",
      "name": "Arimis",
      "symbol": "ARM",
      "decimals": 9,
      "logoURI": "https://easytokenbucket.s3.amazonaws.com/s8sltai23t4ge8mznsvw066qcylh",
      "tags": [
        "utility-token"
      ],
      "extensions": {
      }
    },
    {
      "chainId": 101,
      "address": "6iCVSz4YowpFAxxP76H6vU7tLWgFQ7Ri8UVzptSwiLkm",
      "name": "CRYSTAL ROSE",
      "symbol": "CROSE",
      "decimals": 9,
      "logoURI": "https://easytokenbucket.s3.amazonaws.com/fn3ti43us49bm424ksvtrn7txzji",
      "tags": [
        "utility-token"
      ],
      "extensions": {
      }
    },
    {
      "chainId": 101,
      "address": "EBskFKr5Mw3Wk4DFEUFP1SLr9ofHuHH593cFYncRgx3S",
      "name": "ROSE",
      "symbol": "AK47",
      "decimals": 9,
      "logoURI": "https://easytokenbucket.s3.amazonaws.com/fz7bhe7sqi3y15z88l8otoo1w0xv",
      "tags": [
        "utility-token"
      ],
      "extensions": {
      }
    },
    {
      "chainId": 101,
      "address": "6aQkfYK3Yhn6unVmotZRvW8KseoiB9SBi4YeMbbXyEZt",
      "name": "Direct Relief Token",
      "symbol": "DRT",
      "decimals": 9,
      "logoURI": "https://easytokenbucket.s3.amazonaws.com/ix2cnladrjt97lq29qxroab23iyg",
      "tags": [
        "utility-token"
      ],
      "extensions": {
      }
    },
    {
      "chainId": 101,
      "address": "J8rWt9L7XWx2isXoLmAUSCGtsLqBtJoZciv3hVamkfNH",
      "name": "MAZI LOVE",
      "symbol": "MLE",
      "decimals": 9,
      "logoURI": "https://easytokenbucket.s3.amazonaws.com/bvmn6c92djpay5ojjbuehnzq4oks",
      "tags": [
        "utility-token"
      ],
      "extensions": {
      }
    },
    {
      "chainId": 101,
      "address": "293pPMC9s6rfkZvmJDrFMq9sSwBnaiNHXmoPbP3yCme4",
      "name": "HITWIN PREDICTS",
      "symbol": "HWIN",
      "decimals": 9,
      "logoURI": "https://easytokenbucket.s3.amazonaws.com/1ha8qxlbgp3uneuxmcxrf74ptz01",
      "tags": [
        "utility-token"
      ],
      "extensions": {
      }
    },
    {
      "chainId": 101,
      "address": "cBYn3WxtT5nxjBwuXmr1CX1gpMhM9mfRqGVK2dhJfbD",
      "name": "MAZI MAN",
      "symbol": "MMN",
      "decimals": 9,
      "logoURI": "https://easytokenbucket.s3.amazonaws.com/8i9lvytr43oz8zcstst8d27h66t5",
      "tags": [
        "utility-token"
      ],
      "extensions": {
      }
    },
    {
      "chainId": 101,
      "address": "hmQuMzW4JEXk4avGzC5vt3Xu2C9hMgPEL93WqXWw3Jy",
      "name": "MAZI BABY",
      "symbol": "MBY",
      "decimals": 9,
      "logoURI": "https://easytokenbucket.s3.amazonaws.com/7bxcqko1l4ilk1m1mg9iy5h9l2yf",
      "tags": [
        "utility-token"
      ],
      "extensions": {
      }
    },
    {
      "chainId": 101,
      "address": "HVh1pAscQzT2H7eeZzKyG2Sg1NPRF6EFvsBWkqcsQ4d9",
      "name": "Datum Coin ",
      "symbol": "DAC",
      "decimals": 9,
      "logoURI": "https://easytokenbucket.s3.amazonaws.com/uauv4i9m4e2ydwtnb3cyhg9qmvls",
      "tags": [
        "utility-token"
      ],
      "extensions": {
      }
    },
    {
      "chainId": 101,
      "address": "3RuhzJCn7P8bRWqPHb3S4nR4o58d1XkED6YpsWpZ8sUD",
      "name": "SAVE THE CHILDREN TOKEN",
      "symbol": "STCT",
      "decimals": 9,
      "logoURI": "https://easytokenbucket.s3.amazonaws.com/awb2qeae4c5slausppuvrezptiw5",
      "tags": [
        "utility-token"
      ],
      "extensions": {
      }
    },
    {
      "chainId": 101,
      "address": "AANWetVYysG7mtJrYXKYmrb9RGiydwRRA5LHwYeKcihy",
      "name": "Django Unchain Talent",
      "symbol": "DJO",
      "decimals": 9,
      "logoURI": "https://easytokenbucket.s3.amazonaws.com/fauz6vld2w6eke3af40wdaonl73k",
      "tags": [
        "utility-token"
      ],
      "extensions": {
      }
    },
    {
      "chainId": 101,
      "address": "Gqd7s2Tq2je5TSnUyWe14FLpSnmjxjeH5EeSCKwUB5kE",
      "name": "RENEC SHIBA",
      "symbol": "SINEC",
      "decimals": 3,
      "logoURI": "https://easytokenbucket.s3.amazonaws.com/39pxkxt2rt560whd1oagv9v6uo5k",
      "tags": [
        "utility-token"
      ],
      "extensions": {
      }
    },
    {
      "chainId": 101,
      "address": "EQNa6TcR4SvaCyouerenSeDLDmioma2vxe9UXGDgYpDq",
      "name": "Kilimanjaro tz",
      "symbol": "KILI",
      "decimals": 9,
      "logoURI": "https://easytokenbucket.s3.amazonaws.com/j48ghki2iqszgf165joiwokz988b",
      "tags": [
        "utility-token"
      ],
      "extensions": {
      }
    },
    {
      "chainId": 101,
      "address": "5cKyNxo1hYyMRXL23CSHe4pdTKXMBcsq2QCh1RkWCtHy",
      "name": "Great Eagle Token",
      "symbol": "GET",
      "decimals": 4,
      "logoURI": "https://easytokenbucket.s3.amazonaws.com/z6nwyhexzh0bab1c66vm1lfqmrwb",
      "tags": [
        "utility-token"
      ],
      "extensions": {
      }
    },
    {
      "chainId": 101,
      "address": "HQDS1WeXvbKeWWN9ZTWfwaYs4EXwW6LSNxyPBHfxd4rq",
      "name": "Camanga Parents Legacy",
      "symbol": "CPL",
      "decimals": 9,
      "logoURI": "https://easytokenbucket.s3.amazonaws.com/ju8b4ydn0x700fz5osdyaexnmqx3",
      "tags": [
        "utility-token"
      ],
      "extensions": {
      }
    },
    {
      "chainId": 101,
      "address": "CqNbJnXMZqBXwtdZRrJDBDc9UnpntWo7Qj9iQV5r1wme",
      "name": "Tokenomics",
      "symbol": "TKN",
      "decimals": 4,
      "logoURI": "https://easytokenbucket.s3.amazonaws.com/qyn9tdtbi0e8p8wl5qgbgg7khuza",
      "tags": [
        "utility-token"
      ],
      "extensions": {
      }
    },
    {
      "chainId": 101,
      "address": "FkuiE2HX69QcopGAXHaTZVZ7oNUaPPQF9vcwpfUNcuCW",
      "name": "CR7 SIUUUUU",
      "symbol": "SIUUU",
      "decimals": 9,
      "logoURI": "https://easytokenbucket.s3.amazonaws.com/iw2ymk0r0y4djrx4gx0zo3e56jxb",
      "tags": [
        "utility-token"
      ],
      "extensions": {
      }
    },
    {
      "chainId": 101,
      "address": "9BY2QELFkxtzs6E8ob3GqVHb51KwQYMGizV9NwtbAvWN",
      "name": "Core Renec",
      "symbol": "Crnc",
      "decimals": 4,
      "logoURI": "https://easytokenbucket.s3.amazonaws.com/5gmcw7ddd7eth5ruqdprepkrut45",
      "tags": [
        "utility-token"
      ],
      "extensions": {
      }
    },
    {
      "chainId": 101,
      "address": "J56MhYaGGAj3AhtPeZPVMaZcPMHkn15TccW6ZYhyuf91",
      "name": "CrashCoin",
      "symbol": "CHCN",
      "decimals": 6,
      "logoURI": "https://easytokenbucket.s3.amazonaws.com/vub182irc4rfqwx36jgj11weu6pu",
      "tags": [
        "utility-token"
      ],
      "extensions": {
      }
    },
    {
      "chainId": 101,
      "address": "Fj1EL9LFkNgKuqN745PTGkDb5qGfdVi4nLkJvErgtQMh",
      "name": "SHP BANK CRYPTO",
      "symbol": "SHP",
      "decimals": 9,
      "logoURI": "https://easytokenbucket.s3.amazonaws.com/f4ujvyicd50j39tplwjxwwig4cgz",
      "tags": [
        "utility-token"
      ],
      "extensions": {
      }
    },
    {
      "chainId": 101,
      "address": "5Ld1hPeFjRnYer8YrBDhczu4FTg1aYs6GaiFAHofJ2oE",
      "name": "Zksync ren",
      "symbol": "ZKR",
      "decimals": 9,
      "logoURI": "https://easytokenbucket.s3.amazonaws.com/e4wjq3hywliuhkuat0wjeq0h6o50",
      "tags": [
        "utility-token"
      ],
      "extensions": {
      }
    },
    {
      "chainId": 101,
      "address": "9Pc59Kn7pDUgKoyTX5aqecmoo5BvMcTQB9bsAxTfiDg7",
      "name": "PEPERENEC",
      "symbol": "Peper",
      "decimals": 9,
      "logoURI": "https://easytokenbucket.s3.amazonaws.com/69gk4ek10d0vg1zhkvv06nb1cvxz",
      "tags": [
        "utility-token"
      ],
      "extensions": {
      }
    },
    {
      "chainId": 101,
      "address": "FdToeUUNqhqPUx4sdyJGDzhJvW63bNQm8PJULmq3ZgBp",
      "name": "ShibaKing",
      "symbol": "SKING",
      "decimals": 9,
      "logoURI": "https://easytokenbucket.s3.amazonaws.com/fuf8hyngg4wge8sczbbis1ylp9ew",
      "tags": [
        "utility-token"
      ],
      "extensions": {
      }
    },
    {
      "chainId": 101,
      "address": "BL1UMaBVkGNVQWNzGhGEwSaU61jBydEHVpk48wkvsBcb",
      "name": "CryptoCorgi",
      "symbol": "CORGI",
      "decimals": 9,
      "logoURI": "https://easytokenbucket.s3.amazonaws.com/14udb9igwzptkgvnd9unbb4cu4pw",
      "tags": [
        "utility-token"
      ],
      "extensions": {
      }
    },
    {
      "chainId": 101,
      "address": "6fyk51oQEipYZrE1E7E169UMYpo3fQJ1iTze2mWU9E9z",
      "name": "IROKO KING",
      "symbol": "IRK",
      "decimals": 9,
      "logoURI": "https://easytokenbucket.s3.amazonaws.com/pib3nuimf3l8txaqt2n889ya2jub",
      "tags": [
        "utility-token"
      ],
      "extensions": {
      }
    },
    {
      "chainId": 101,
      "address": "B3ySSb4w6cjb2eHRoiaUcGvrttdSvNBuiDXDvhLRjUFs",
      "name": "Pooh Token",
      "symbol": "POOH",
      "decimals": 9,
      "logoURI": "https://easytokenbucket.s3.amazonaws.com/mezjspm2rc6759o2as3dbsifqkwc",
      "tags": [
        "utility-token"
      ],
      "extensions": {
      }
    },
    {
      "chainId": 101,
      "address": "6UeFNrG49uiJP49bxy79wD9eL9j1FFEymjq71ZiQ9VWA",
      "name": "FIRE COIN",
      "symbol": "FRC",
      "decimals": 9,
      "logoURI": "https://easytokenbucket.s3.amazonaws.com/nuo8snpjd5g974bq2kyh472016ri",
      "tags": [
        "utility-token"
      ],
      "extensions": {
      }
    },
    {
      "chainId": 101,
      "address": "Fmu9WEYt7ShD5gjjvirHAWWb2dkWHKSnFxM4PcUaVvd",
      "name": "JERRY Coin",
      "symbol": "JERRY",
      "decimals": 9,
      "logoURI": "https://easytokenbucket.s3.amazonaws.com/xrfz7vlo9q6ach3o8227ge2x2fqb",
      "tags": [
        "utility-token"
      ],
      "extensions": {
      }
    },
    {
      "chainId": 101,
      "address": "9mAmV1ownPjdr8kgquXZdJ9qhsC2NsryNWddbbAKzk3X",
      "name": "MOSA Wookies Dreamer",
      "symbol": "MOSA",
      "decimals": 9,
      "logoURI": "https://easytokenbucket.s3.amazonaws.com/82phsixkq8knmmlesqfczbedtovc",
      "tags": [
        "utility-token"
      ],
      "extensions": {
      }
    },
    {
      "chainId": 101,
      "address": "3GddmfSkGWkkkCCvLyorKVupoeErxKCoKas3iRM6XtzQ",
      "name": "Make Money Online",
      "symbol": "MMO",
      "decimals": 9,
      "logoURI": "https://easytokenbucket.s3.amazonaws.com/st22h1lef8m6octxgqv0w44kpv3h",
      "tags": [
        "utility-token"
      ],
      "extensions": {
      }
    },
    {
      "chainId": 101,
      "address": "3Lh1LjdZaVj8YiGXAVr9qmp1ovimn4ZiZJczBv7RzjLL",
      "name": "PiNetworkBlog",
      "symbol": "PNB",
      "decimals": 9,
      "logoURI": "https://easytokenbucket.s3.amazonaws.com/960i7fh5zjcnozgumy226gk54wtp",
      "tags": [
        "utility-token"
      ],
      "extensions": {
      }
    },
    {
      "chainId": 101,
      "address": "6UspTHNENZoDDxwbnWRPNxMFGS2Jk8oNye4WHiWafvJy",
      "name": "Tplus Invest Group",
      "symbol": "TPLUS",
      "decimals": 8,
      "logoURI": "https://easytokenbucket.s3.amazonaws.com/8piydekzratc4gyd0y5gmisg4524",
      "tags": [
        "utility-token"
      ],
      "extensions": {
      }
    },
    {
      "chainId": 101,
      "address": "9uWqsr6WZnVBXKci8vqy6robUVYRZrVeFcH568AKRXZE",
      "name": "lulu",
      "symbol": "LULU",
      "decimals": 9,
      "logoURI": "https://easytokenbucket.s3.amazonaws.com/pcu5bmomiwfurwmwtqseu5644vg0",
      "tags": [
        "utility-token"
      ],
      "extensions": {
      }
    },
    {
      "chainId": 101,
      "address": "brXCxNcK455xXWZ3u5YiJ6u5AhxzTBD4g1SwEFFkuZt",
      "name": "GoldCoin",
      "symbol": "GOLD",
      "decimals": 9,
      "logoURI": "https://easytokenbucket.s3.amazonaws.com/euzz96ml1w9r67qv8y13z2dz39fu",
      "tags": [
        "utility-token"
      ],
      "extensions": {
      }
    },
    {
      "chainId": 101,
      "address": "J6kVA7jTYFujGAtuggBBtpPPHBiZhgUdE3qiCrvGqFZZ",
      "name": "KC",
      "symbol": "KC",
      "decimals": 9,
      "logoURI": "https://easytokenbucket.s3.amazonaws.com/7gjbf533pm0fnw0hmzn3buinewvo",
      "tags": [
        "utility-token"
      ],
      "extensions": {
      }
    },
    {
      "chainId": 101,
      "address": "AQQPhfKNiH1MSqex22nKk2iDbT4vN2QLzbg5muKCCKeV",
      "name": "shibu",
      "symbol": "SHIBU",
      "decimals": 9,
      "logoURI": "https://easytokenbucket.s3.amazonaws.com/ktq0gpnbn7utmci5lojtvsuv4hj1",
      "tags": [
        "utility-token"
      ],
      "extensions": {
      }
    },
    {
      "chainId": 101,
      "address": "8KuABXWXJJwCCbNzHR3JQntc7Emw6pptKnv5vpMEp6W1",
      "name": "FUN",
      "symbol": "FUN",
      "decimals": 4,
      "logoURI": "https://easytokenbucket.s3.amazonaws.com/kzw8deikll6gqdpu1ol9a2i92mcw",
      "tags": [
        "utility-token"
      ],
      "extensions": {
      }
    },
    {
      "chainId": 101,
      "address": "EqGLWRs3Pc6hz164tKF13HRdpxWspdhM5xyq4GU43wh2",
      "name": "Millionaire Coin",
      "symbol": "MCOIN",
      "decimals": 9,
      "logoURI": "https://easytokenbucket.s3.amazonaws.com/3kt5hqt72xfagjkj842taxhyf6rr",
      "tags": [
        "utility-token"
      ],
      "extensions": {
      }
    },
    {
      "chainId": 101,
      "address": "6g7pZfaJNq2CwKvgbcdCxvcHmnaD8TTejVXuqr5orsEY",
      "name": "polainu",
      "symbol": "pln",
      "decimals": 9,
      "logoURI": "https://easytokenbucket.s3.amazonaws.com/wxmewm0qr0i13os3nmsntnc82av9",
      "tags": [
        "utility-token"
      ],
      "extensions": {
      }
    },
    {
      "chainId": 101,
      "address": "247DjLcbAFjRQvPbttmde7C1e6jFpomsrMhoFrLANopR",
      "name": "Dragon Ffy Token",
      "symbol": "DFT",
      "decimals": 9,
      "logoURI": "https://easytokenbucket.s3.amazonaws.com/06kwbyi7obdxi2rfwri7ionv9ivt",
      "tags": [
        "utility-token"
      ],
      "extensions": {
      }
    },
    {
      "chainId": 101,
      "address": "8RxGEw45uiDfffDMJvG7bBfFpq9LA8UAex1M1u6VKeV2",
      "name": "Whale",
      "symbol": "WHALE",
      "decimals": 9,
      "logoURI": "https://easytokenbucket.s3.amazonaws.com/n8bq9mhdj93ew8zxcfrlf5q78quk",
      "tags": [
        "utility-token"
      ],
      "extensions": {
      }
    },
    {
      "chainId": 101,
      "address": "9WKVqvxhdYh8Q5UjaeeZZ6qRuoaPqHLTVN5KZKrvcwCh",
      "name": "Baby Shark",
      "symbol": "BBS",
      "decimals": 9,
      "logoURI": "https://easytokenbucket.s3.amazonaws.com/vu8xsvpujswpzd8q13s8z7ub0q3r",
      "tags": [
        "utility-token"
      ],
      "extensions": {
      }
    },
    {
      "chainId": 101,
      "address": "8Py1G5ookonx1qmCe8ec818gD5qFqeMvYnmD3sjkfnTi",
      "name": "hextracoin",
      "symbol": "HXT",
      "decimals": 9,
      "logoURI": "https://easytokenbucket.s3.amazonaws.com/z2g3jpo5c2x1h2ke0gfxdz2eadw6",
      "tags": [
        "utility-token"
      ],
      "extensions": {
      }
    },
    {
      "chainId": 101,
      "address": "7NYwhFJLRUhBo8r6E2wuYJ86cee4LXG1mZKJB4HQC49m",
      "name": "ANNURY TOKEN ",
      "symbol": "ANUT",
      "decimals": 9,
      "logoURI": "https://easytokenbucket.s3.amazonaws.com/uaiu2v38saq0c78vrxapvzq08av6",
      "tags": [
        "utility-token"
      ],
      "extensions": {
      }
    },
    {
      "chainId": 101,
      "address": "A1U33Siaby9dAL1kkabFeXyqZXC7hudcSmhTeg9xV9v1",
      "name": "Pool",
      "symbol": "POOL",
      "decimals": 9,
      "logoURI": "https://easytokenbucket.s3.amazonaws.com/2hr3bkui84x0bx8rm9krhzrxy3jp",
      "tags": [
        "utility-token"
      ],
      "extensions": {
      }
    },
    {
      "chainId": 101,
      "address": "9fckZTkB9Zx13G483WY6tAiCL2KhnqAYtd94vTNg2G7v",
      "name": "FCARE247",
      "symbol": "FC247",
      "decimals": 9,
      "logoURI": "https://easytokenbucket.s3.amazonaws.com/i41ns1wtauukeuqm2on74g60f8ek",
      "tags": [
        "utility-token"
      ],
      "extensions": {
      }
    },
    {
      "chainId": 101,
      "address": "CeBu2iTwnqY8wqLMp7YkPVn95JjEQDYZJEw9FECuci2K",
      "name": "COCKROACH COIN",
      "symbol": "ROACH",
      "decimals": 9,
      "logoURI": "https://easytokenbucket.s3.amazonaws.com/sx0fvkrjc45ehryxklwpixh1s2in",
      "tags": [
        "utility-token"
      ],
      "extensions": {
      }
    },
    {
      "chainId": 101,
      "address": "32ufdNq676GsGTj3QQXAqHx9ySgLDaajJdaxMDVmardj",
      "name": "SHTV Coin",
      "symbol": "SHTVC",
      "decimals": 9,
      "logoURI": "https://easytokenbucket.s3.amazonaws.com/tfvyedtheakg8k1idm77vxu9oqrz",
      "tags": [
        "utility-token"
      ],
      "extensions": {
      }
    },
    {
      "chainId": 101,
      "address": "BgNZK6K6dMidQ8EaeWwBgrM72LFz3JAttwUWvSgUATFJ",
      "name": "BIGPRO Coin",
      "symbol": "BPR",
      "decimals": 9,
      "logoURI": "https://easytokenbucket.s3.amazonaws.com/vlv6uq48uorck8hxpgc2sl78yvt4",
      "tags": [
        "utility-token"
      ],
      "extensions": {
      }
    },
    {
      "chainId": 101,
      "address": "5NMezo7bLPSQGrBzcqQRDMXHY8r3zMa2zQ4XkUVkk9wK",
      "name": "adalinewudsl",
      "symbol": "grace",
      "decimals": 9,
      "logoURI": "https://easytokenbucket.s3.amazonaws.com/99u5dritylsm3iory5lbntg0htjb",
      "tags": [
        "utility-token"
      ],
      "extensions": {
      }
    },
    {
      "chainId": 101,
      "address": "HFWSRYfGj8L3NqCSHh2UTu4L7RpNjZvhUBagupcYCsSr",
      "name": "AVIVA",
      "symbol": "AVI",
      "decimals": 9,
      "logoURI": "https://easytokenbucket.s3.amazonaws.com/b1xpd4jh467psmyyes78cg7mfpeg",
      "tags": [
        "utility-token"
      ],
      "extensions": {
      }
    },
    {
      "chainId": 101,
      "address": "5coumXCR1qzrSxhrpfMCKsetxs1cHt1TE1neGp4srZsE",
      "name": "NEXUS",
      "symbol": "NEX",
      "decimals": 9,
      "logoURI": "https://easytokenbucket.s3.amazonaws.com/9mxy881mfhs32rqgxb9uyayxgmms",
      "tags": [
        "utility-token"
      ],
      "extensions": {
      }
    },
    {
      "chainId": 101,
      "address": "3wMaa3qZFQMUzy8LFG5n8r6fDtFEqV4oyFnta22jiLRG",
      "name": "SWALASWAP",
      "symbol": "SWALA",
      "decimals": 8,
      "logoURI": "https://easytokenbucket.s3.amazonaws.com/m3xmainjwqhi8lisd39gx9d5tbie",
      "tags": [
        "utility-token"
      ],
      "extensions": {
      }
    },
    {
      "chainId": 101,
      "address": "3Af4GrD4fCZ6S1uArwVxwo8GgtHn6G4Ye6an8JJuZ5kz",
      "name": " Inu Iced Milk Coffee",
      "symbol": "IIMC",
      "decimals": 2,
      "logoURI": "https://easytokenbucket.s3.amazonaws.com/rnolyvzpbz1j906djiqaesck6ycc",
      "tags": [
        "utility-token"
      ],
      "extensions": {
      }
    },
    {
      "chainId": 101,
      "address": "2NfKjxetMeScv9k2z5mNPbeE2u7CwmaHVCzptQBSJJ3F",
      "name": "Kosova",
      "symbol": "KS",
      "decimals": 9,
      "logoURI": "https://easytokenbucket.s3.amazonaws.com/5cjeeb6nhs8x337jv5mo7e1w9vmj",
      "tags": [
        "utility-token"
      ],
      "extensions": {
      }
    },
    {
      "chainId": 101,
      "address": "8ZvzYygSLU6yUUF1VGWGwmpe49B2RSfLV4mf6VwCTKs9",
      "name": "Elites",
      "symbol": "ELT",
      "decimals": 9,
      "logoURI": "https://easytokenbucket.s3.amazonaws.com/r7k8p2j7rlez6sceb5deyrtp11fu",
      "tags": [
        "utility-token"
      ],
      "extensions": {
      }
    },
    {
      "chainId": 101,
      "address": "Fe3q1rMW4gHGpL1wGrmq5NpkcxZg4Y2ktm5ifs1Bf5cR",
      "name": "Happy",
      "symbol": "HAP",
      "decimals": 9,
      "logoURI": "https://easytokenbucket.s3.amazonaws.com/kxekwn1orgw5gr98um9l1pl8d3af",
      "tags": [
        "utility-token"
      ],
      "extensions": {
      }
    },
    {
      "chainId": 101,
      "address": "BqKBgncoSH6uwHoHqArF4dofo9or3kPWP9K6WZJEMeQh",
      "name": "BITCOPPER TOKEN",
      "symbol": "BITCO",
      "decimals": 9,
      "logoURI": "https://easytokenbucket.s3.amazonaws.com/0otfh1unnoq16dzxgj22ufniqv1f",
      "tags": [
        "utility-token"
      ],
      "extensions": {
      }
    },
    {
      "chainId": 101,
      "address": "NzsZVw9MUF723oTSTR3nNLtUNipPjhsy21xkZDGddLe",
      "name": "AVIVA COIN",
      "symbol": "AVIVA",
      "decimals": 9,
      "logoURI": "https://easytokenbucket.s3.amazonaws.com/kgsqrdattzpyve57ydxkhc0jk86m",
      "tags": [
        "utility-token"
      ],
      "extensions": {
      }
    },
    {
      "chainId": 101,
      "address": "GB1Hg9d3KkRsGp2XFKuVGL28aCTFbBdmADLMSvh5AVvA",
      "name": "Lemonade",
      "symbol": "LMN",
      "decimals": 9,
      "logoURI": "https://easytokenbucket.s3.amazonaws.com/kzm1wtjgr08ztz97pm2ie7pifjn8",
      "tags": [
        "utility-token"
      ],
      "extensions": {
      }
    },
    {
      "chainId": 101,
      "address": "ELhKjrU1QNEgpQ3qeXmbhfKaa3kiXYVS3A5ZrGrV7Qsb",
      "name": "ValorCoin",
      "symbol": "valor",
      "decimals": 9,
      "logoURI": "https://easytokenbucket.s3.amazonaws.com/o80tdl76b6k4g10qjuldhmohjcgr",
      "tags": [
        "utility-token"
      ],
      "extensions": {
      }
    },
    {
      "chainId": 101,
      "address": "Hiynjic5ekbZBEBU73KN5RaAdkLUcGDW6sYfST431BYt",
      "name": "PulseChain Classic",
      "symbol": "PLSC",
      "decimals": 9,
      "logoURI": "https://easytokenbucket.s3.amazonaws.com/pr3y9re8xdhzd1cxls846mh6cpdz",
      "tags": [
        "utility-token"
      ],
      "extensions": {
      }
    },
    {
      "chainId": 101,
      "address": "5PBSPXbaGpextUbrjJ3NxCQyPBkPPF9QcMYms7JpDxF1",
      "name": "RENEC PAD",
      "symbol": "rePAD",
      "decimals": 9,
      "logoURI": "https://easytokenbucket.s3.amazonaws.com/0witihg8gg38sjuj4z7qymimnlod",
      "tags": [
        "utility-token"
      ],
      "extensions": {
      }
    },
    {
      "chainId": 101,
      "address": "H1Cwjnq2Fyf46EDdn7VrabdL5nuqFA5nGUBbN7K19T8t",
      "name": "Dinochrome",
      "symbol": "Dino",
      "decimals": 9,
      "logoURI": "https://easytokenbucket.s3.amazonaws.com/b8sinx8hjq09uc7b01qkgvtxbkp3",
      "tags": [
        "utility-token"
      ],
      "extensions": {
      }
    },
    {
      "chainId": 101,
      "address": "za78GrpSzs7ny5vUoqv9oUoySZDwgDNumnc5sDEEsZM",
      "name": "HASAGi",
      "symbol": "YASUO",
      "decimals": 2,
      "logoURI": "https://easytokenbucket.s3.amazonaws.com/av6y2ezw5mdci68l46svaa8pyao1",
      "tags": [
        "utility-token"
      ],
      "extensions": {
      }
    },
    {
      "chainId": 101,
      "address": "DfocEzYgAjkwHam2LjxpqiWqdzse6fCFCv4coL3pnYq5",
      "name": "RULER",
      "symbol": "ZERI",
      "decimals": 9,
      "logoURI": "https://easytokenbucket.s3.amazonaws.com/vob9g0gd73qgfbpinee2gyyxxhdv",
      "tags": [
        "utility-token"
      ],
      "extensions": {
      }
    },
    {
      "chainId": 101,
      "address": "14gBdATCTo5k3TGZMvtm8hyGhdfQht2uc5RGeRM5rqdw",
      "name": "BANG",
      "symbol": "LUCIA",
      "decimals": 9,
      "logoURI": "https://easytokenbucket.s3.amazonaws.com/4uhtj8lx4uo3gm556okhndinnmvz",
      "tags": [
        "utility-token"
      ],
      "extensions": {
      }
    },
    {
      "chainId": 101,
      "address": "CJLLjKp4m791xXaMySQhB9nM9RueCiNYGJjPDgy7rtTq",
      "name": "Warrior",
      "symbol": "WRR",
      "decimals": 9,
      "logoURI": "https://easytokenbucket.s3.amazonaws.com/xklnm668qt29itf21mmwcubd25ch",
      "tags": [
        "utility-token"
      ],
      "extensions": {
      }
    },
    {
      "chainId": 101,
      "address": "BWv7FZQF699uvE3T9WwHRBfoFpsyirXxteFQPwjyVds9",
      "name": "Renec Crowd1 Foundation Coin",
      "symbol": "RC1",
      "decimals": 9,
      "logoURI": "https://easytokenbucket.s3.amazonaws.com/oydytvpfikih0ys5nkknc8k72fc0",
      "tags": [
        "utility-token"
      ],
      "extensions": {
      }
    },
    {
      "chainId": 101,
      "address": "5cSYAHHWNAmULDwm9W8G8vvu4DXRCAqWqV48x3q9poJf",
      "name": "USD SHP BANK CRYPTO",
      "symbol": "USHP",
      "decimals": 9,
      "logoURI": "https://easytokenbucket.s3.amazonaws.com/8fwaslfr8tgnaw5h9ckof3kt2zlc",
      "tags": [
        "utility-token"
      ],
      "extensions": {
      }
    },
    {
      "chainId": 101,
      "address": "8sgQtL6eDDyYUM8EhuiuN4dn2qWcKjuZZYctNbUHjGT8",
      "name": "Tea 4",
      "symbol": "TEA4",
      "decimals": 9,
      "logoURI": "https://easytokenbucket.s3.amazonaws.com/dw7gzjqvpt7pfcb5cnztp8628t76",
      "tags": [
        "utility-token"
      ],
      "extensions": {
      }
    },
    {
      "chainId": 101,
      "address": "GfwLr6EFUaXxuxMCd43FLvsvAytbFsvMY9SEnp88VpYn",
      "name": "Coffee bean",
      "symbol": "BEAN",
      "decimals": 9,
      "logoURI": "https://easytokenbucket.s3.amazonaws.com/imt4uowuxyjg89f9iqc14ma28rcn",
      "tags": [
        "utility-token"
      ],
      "extensions": {
      }
    },
    {
      "chainId": 101,
      "address": "APdL6mZNx5XJtncWkwuyXY5PRa3o11JEqHzWjSUSBYE5",
      "name": "YASUOOO",
      "symbol": "YAH",
      "decimals": 9,
      "logoURI": "https://easytokenbucket.s3.amazonaws.com/sy8oh71ijxeqq4m0uvfkezmsifgn",
      "tags": [
        "utility-token"
      ],
      "extensions": {
      }
    },
    {
      "chainId": 101,
      "address": "4S3HzeK9nmxyujNWhWGpb4zqbzAXZU41rByV5ZL3w9QL",
      "name": "Nudge",
      "symbol": "NDG",
      "decimals": 9,
      "logoURI": "https://easytokenbucket.s3.amazonaws.com/vrwstr2hj8bokeaj27zfmkdfih9i",
      "tags": [
        "utility-token"
      ],
      "extensions": {
      }
    },
    {
      "chainId": 101,
      "address": "8C4N6YbnQ8yrwrrqppA7ndKUzLUS1j4uKsmX18ZFrXdn",
      "name": "League Of Legends Fan",
      "symbol": "LOL",
      "decimals": 0,
      "logoURI": "https://easytokenbucket.s3.amazonaws.com/s89y54ova3x3bsk75uyrxo3886nk",
      "tags": [
        "utility-token"
      ],
      "extensions": {
      }
    },
    {
      "chainId": 101,
      "address": "EYgZmcqobBHBN78MxJgGNBi2GLLx9cGJwVy6tNbENUmR",
      "name": "Tea",
      "symbol": "TEA",
      "decimals": 9,
      "logoURI": "https://easytokenbucket.s3.amazonaws.com/bayln5ni4phh39va31gb17i9504y",
      "tags": [
        "utility-token"
      ],
      "extensions": {
      }
    },
    {
      "chainId": 101,
      "address": "FZgF3bsrKCiKRrwQyvefM33ZgWyPCKv3a7o1AUgzVSNJ",
      "name": "RHORSE",
      "symbol": "RHE",
      "decimals": 9,
      "logoURI": "https://easytokenbucket.s3.amazonaws.com/gomyy2hy226rdjd95qun9z39u64k",
      "tags": [
        "utility-token"
      ],
      "extensions": {
      }
    },
    {
      "chainId": 101,
      "address": "C5nRPTi9V2TVuNhEP9AoDYQXjshP76Mavc5JFMsDRPTm",
      "name": "CryptoChameleon",
      "symbol": "CCN",
      "decimals": 9,
      "logoURI": "https://easytokenbucket.s3.amazonaws.com/fbykg80z6pbo1rhmxx2kv13wa6lg",
      "tags": [
        "utility-token"
      ],
      "extensions": {
      }
    },
    {
      "chainId": 101,
      "address": "zqk4tpVBRDPoQdRUSHxPmyNYVvD87Ec2Ji2RrAMwGD1",
      "name": "HEN COIN",
      "symbol": "HNC",
      "decimals": 9,
      "logoURI": "https://easytokenbucket.s3.amazonaws.com/6om38hrsztub9g0gisq60zv7jcxn",
      "tags": [
        "utility-token"
      ],
      "extensions": {
      }
    },
    {
      "chainId": 101,
      "address": "CMy2ZuSeqwVYo4hnKbTTzQGJnA7QBAzK7fcwpEtJhS6L",
      "name": "RBALL",
      "symbol": "RBL",
      "decimals": 9,
      "logoURI": "https://easytokenbucket.s3.amazonaws.com/hqrel6ol6pm4brnzyegi9k60zcbj",
      "tags": [
        "utility-token"
      ],
      "extensions": {
      }
    },
    {
      "chainId": 101,
      "address": "Ad3q614Jm61mi7DepHoo4Fy8w9fFggmdiPAM3AaqzXnM",
      "name": "BullBear",
      "symbol": "BBR",
      "decimals": 9,
      "logoURI": "https://easytokenbucket.s3.amazonaws.com/4o32w4c40p8fkg33ozrqxytuodql",
      "tags": [
        "utility-token"
      ],
      "extensions": {
      }
    },
    {
      "chainId": 101,
      "address": "GGzQxfKCVyGNXXNPLtC5EnoRuFCogf8EvtXVLZ6uda7J",
      "name": "GigaGator",
      "symbol": "GGTR",
      "decimals": 9,
      "logoURI": "https://easytokenbucket.s3.amazonaws.com/pdcbci0ypc1itkgo7qiyza8hykne",
      "tags": [
        "utility-token"
      ],
      "extensions": {
      }
    },
    {
      "chainId": 101,
      "address": "Dhvx5dnMgZmew3At5b6bji2qP4yWcQYTYrWbPzsfYir",
      "name": "PizzaPlanet",
      "symbol": "PZZPL",
      "decimals": 9,
      "logoURI": "https://easytokenbucket.s3.amazonaws.com/xz8mfphp6vq9ihjn3n08gyljjckn",
      "tags": [
        "utility-token"
      ],
      "extensions": {
      }
    },
    {
      "chainId": 101,
      "address": "BdGD9u8mBJyzmg23WqjHnd6XTYkkA3Kq6NEAeW4Pnjyh",
      "name": "MonkeyMoon",
      "symbol": "MM",
      "decimals": 9,
      "logoURI": "https://easytokenbucket.s3.amazonaws.com/4q13m4k1d1ezv8xu3uv0r364cyar",
      "tags": [
        "utility-token"
      ],
      "extensions": {
      }
    },
    {
      "chainId": 101,
      "address": "6L8hBZYA3rk5e8BopZTMwrq9asfFWLn9jLTMWfmfQeMh",
      "name": "MAIZE CORN",
      "symbol": "MAC",
      "decimals": 9,
      "logoURI": "https://easytokenbucket.s3.amazonaws.com/pplpstrxtl89hjtp6mci02f2nn57",
      "tags": [
        "utility-token"
      ],
      "extensions": {
      }
    },
    {
      "chainId": 101,
      "address": "GvkLa5oT4vBMHL3KFt7B5drhUbHWPi3jEi3DBmP1Wikf",
      "name": "XL",
      "symbol": "XL",
      "decimals": 9,
      "logoURI": "https://easytokenbucket.s3.amazonaws.com/ecegn2w3hg8x1tmgrn3t4fx7y6nx",
      "tags": [
        "utility-token"
      ],
      "extensions": {
      }
    }
  ],
  "version": {
    "major": 0,
    "minor": 3,
    "patch": 3
  }
}